SDGPy/SDGpy.py
sdgpy-0.1.0.dist-info/LICENSE
sdgpy-0.1.0.dist-info/METADATA
sdgpy-0.1.0.dist-info/WHEEL
sdgpy-0.1.0.dist-info/RECORD
